{"page":519,"ayahs":[{"surahNumber":50,"surahName":"سُورَةُ قٓ","surahEnglishName":"Qaaf","ayahNumber":16,"text":"وَلَقَدْ|And certainly|107|116|640$خَلَقْنَا|We created|97|115|7029$ٱلْإِنسَـٰنَ|man|90|108|8037$وَنَعْلَمُ|and We know|109|127|16051$مَا|what|53|71|262$تُوَسْوِسُ|whispers|99|117|16052$بِهِۦ|to him|61|70|204$نَفْسُهُۥ‌ۖ|his soul,|80|97|4907$وَنَحْنُ|and We|76|110|319$أَقْرَبُ|(are) nearer|100|134|2126$إِلَيْهِ|to him|61|95|296$مِنْ|than|50|84|53$حَبْلِ ٱلْوَرِيدِ|(his) jugular vein.|136|153|16053$","juz":26,"ruku":453,"manzil":7,"hizbQuarter":207,"sajda":false,"isSurahStart":false},{"surahNumber":50,"surahName":"سُورَةُ قٓ","surahEnglishName":"Qaaf","ayahNumber":17,"text":"إِذْ|When|57|71|1198$يَتَلَقَّى|receive|70|99|16054$ٱلْمُتَلَقِّيَانِ|the two receivers|137|166|16055$عَنِ|on|54|83|1663$ٱلْيَمِينِ|the right|80|109|9978$وَعَنِ|and on|68|97|5229$ٱلشِّمَالِ|the left|87|101|10652$قَعِيدٌ|seated.|70|70|16056$","juz":26,"ruku":453,"manzil":7,"hizbQuarter":207,"sajda":false,"isSurahStart":false},{"surahNumber":50,"surahName":"سُورَةُ قٓ","surahEnglishName":"Qaaf","ayahNumber":18,"text":"مَّا|Not|43|53|262$يَلْفِظُ|he utters|81|100|16057$مِن|any|50|69|53$قَوْلٍ|word|59|78|16058$إِلَّا|but|42|61|86$لَدَيْهِ|with him|75|94|11003$رَقِيبٌ|(is) an observer|125|144|8712$عَتِيدٌ|ready.|64|74|16059$","juz":26,"ruku":453,"manzil":7,"hizbQuarter":207,"sajda":false,"isSurahStart":false},{"surahNumber":50,"surahName":"سُورَةُ قٓ","surahEnglishName":"Qaaf","ayahNumber":19,"text":"وَجَآءَتْ|And will come|110|120|8876$سَكْرَةُ|(the) stupor|101|122|16060$ٱلْمَوْتِ|(of) death|88|108|166$بِٱلْحَقِّ‌ۖ|in truth,|78|98|692$ذَٲلِكَ|`That|64|84|28$مَا|(is) what|80|100|262$كُنتَ|you were|81|91|1281$مِنْهُ|[from it]|75|332|571$تَحِيدُ|avoiding.`|87|344|16061$","juz":26,"ruku":453,"manzil":7,"hizbQuarter":207,"sajda":false,"isSurahStart":false},{"surahNumber":50,"surahName":"سُورَةُ قٓ","surahEnglishName":"Qaaf","ayahNumber":20,"text":"وَنُفِخَ|And will be blown|134|143|11032$فِى|[in]|48|66|89$ٱلصُّورِ‌ۚ|the trumpet.|104|122|5734$ذَٲلِكَ|That|64|82|28$يَوْمُ|(is the) Day|99|117|5399$ٱلْوَعِيدِ|(of) the Warning.|135|144|11648$","juz":26,"ruku":453,"manzil":7,"hizbQuarter":207,"sajda":false,"isSurahStart":false},{"surahNumber":50,"surahName":"سُورَةُ قٓ","surahEnglishName":"Qaaf","ayahNumber":21,"text":"وَجَآءَتْ|And will come|110|129|8876$كُلُّ|every|57|95|575$نَفْسٍ|soul,|62|100|2507$مَّعَهَا|with it|66|104|16062$سَآئِقٌ|a driver|71|109|16063$وَشَهِيدٌ|and a witness.|117|136|16064$","juz":26,"ruku":453,"manzil":7,"hizbQuarter":207,"sajda":false,"isSurahStart":false},{"surahNumber":50,"surahName":"سُورَةُ قٓ","surahEnglishName":"Qaaf","ayahNumber":22,"text":"لَّقَدْ|`Certainly|86|97|3466$كُنتَ|you were|81|103|1281$فِى|in|48|70|89$غَفْلَةٍ|heedlessness|107|129|11195$مِّنْ|of|50|72|53$هَـٰذَا|this.|59|81|248$فَكَشَفْنَا|So We have removed|161|172|11887$عَنكَ|from you|78|107|1109$غِطَآءَكَ|your cover,|96|154|16065$فَبَصَرُكَ|so your sight|106|164|16066$ٱلْيَوْمَ|today|67|125|2217$حَدِيدٌ|(is) sharp.`|96|125|16067$","juz":26,"ruku":453,"manzil":7,"hizbQuarter":207,"sajda":false,"isSurahStart":false},{"surahNumber":50,"surahName":"سُورَةُ قٓ","surahEnglishName":"Qaaf","ayahNumber":23,"text":"وَقَالَ|And (will) say|110|124|1089$قَرِينُهُۥ|his companion,|118|146|16068$هَـٰذَا|`This|59|87|248$مَا|(is) what|80|108|262$لَدَىَّ|(is) with me|99|127|13114$عَتِيدٌ|ready.`|70|84|16059$","juz":26,"ruku":453,"manzil":7,"hizbQuarter":207,"sajda":false,"isSurahStart":false},{"surahNumber":50,"surahName":"سُورَةُ قٓ","surahEnglishName":"Qaaf","ayahNumber":24,"text":"أَلْقِيَا|`Throw|69|95|16069$فِى|into|48|100|89$جَهَنَّمَ|Hell|69|121|2655$كُلَّ|every|57|109|2487$كَفَّارٍ|disbeliever|89|141|2488$عَنِيدٍ|stubborn,|83|109|8567$","juz":26,"ruku":453,"manzil":7,"hizbQuarter":207,"sajda":false,"isSurahStart":false},{"surahNumber":50,"surahName":"سُورَةُ قٓ","surahEnglishName":"Qaaf","ayahNumber":25,"text":"مَّنَّاعٍ|Forbidder|81|137|16070$لِّلْخَيْرِ|of good,|75|187|16071$مُعْتَدٍ|transgressor|102|214|16072$مُّرِيبٍ|doubter,|80|136|8582$","juz":26,"ruku":453,"manzil":7,"hizbQuarter":207,"sajda":false,"isSurahStart":false},{"surahNumber":50,"surahName":"سُورَةُ قٓ","surahEnglishName":"Qaaf","ayahNumber":26,"text":"ٱلَّذِى|Who|65|79|138$جَعَلَ|made|66|94|195$مَعَ|with|48|76|443$ٱللَّهِ|Allah|53|81|606$إِلَـٰهًا|a god|61|89|1222$ءَاخَرَ|another;|77|105|9861$فَأَلْقِيَاهُ|so throw him|105|133|16073$فِى|in(to)|57|71|89$ٱلْعَذَابِ|the punishment|122|346|482$ٱلشَّدِيدِ|the severe.`|104|328|16074$","juz":26,"ruku":453,"manzil":7,"hizbQuarter":207,"sajda":false,"isSurahStart":false},{"surahNumber":50,"surahName":"سُورَةُ قٓ","surahEnglishName":"Qaaf","ayahNumber":27,"text":"۞ قَالَ|Will say|96|109|309$قَرِينُهُۥ|his companion,|118|144|16068$رَبَّنَا|`Our Lord,|89|115|1167$مَآ|not|42|68|262$أَطْغَيْتُهُۥ|I made him transgress,|171|197|16075$وَلَـٰكِن|but|78|91|108$كَانَ|he was|67|138|913$فِى|in|48|189|89$ضَلَـٰلِۭ|error|77|218|3468$بَعِيدٍ|far.`|60|130|1514$","juz":26,"ruku":453,"manzil":7,"hizbQuarter":208,"sajda":false,"isSurahStart":false},{"surahNumber":50,"surahName":"سُورَةُ قٓ","surahEnglishName":"Qaaf","ayahNumber":28,"text":"قَالَ|He will say,|95|106|309$لَا|`(Do) not|84|105|30$تَخْتَصِمُواْ|dispute|114|135|16076$لَدَىَّ|(in) My presence|132|153|13114$وَقَدْ|and indeed,|97|118|2117$قَدَّمْتُ|I sent forth|96|107|16077$إِلَيْكُم|to you|66|318|2453$بِٱلْوَعِيدِ|the Warning.|105|357|16078$","juz":26,"ruku":453,"manzil":7,"hizbQuarter":208,"sajda":false,"isSurahStart":false},{"surahNumber":50,"surahName":"سُورَةُ قٓ","surahEnglishName":"Qaaf","ayahNumber":29,"text":"مَا|Not|43|61|262$يُبَدَّلُ|will be changed|122|157|16079$ٱلْقَوْلُ|the word|79|114|8490$لَدَىَّ|with Me,|77|112|13114$وَمَآ|and not|71|106|46$أَنَا۟|I Am|50|85|2308$بِظَلَّـٰمٍ|unjust|72|90|3561$لِّلْعَبِيدِ|to My slaves.`|117|117|3562$","juz":26,"ruku":453,"manzil":7,"hizbQuarter":208,"sajda":false,"isSurahStart":false},{"surahNumber":50,"surahName":"سُورَةُ قٓ","surahEnglishName":"Qaaf","ayahNumber":30,"text":"يَوْمَ|(The) Day|87|100|1057$نَقُولُ|We will say|94|120|5491$لِجَهَنَّمَ|to Hell,|76|102|7016$هَلِ|`Are|50|76|16080$ٱمْتَلَأْتِ|you filled?`|94|120|16081$وَتَقُولُ|And it will say,|117|143|16082$هَلْ|`Are|50|63|1829$مِن|(there) any|96|352|53$مَّزِيدٍ|more?`|68|324|16083$","juz":26,"ruku":454,"manzil":7,"hizbQuarter":208,"sajda":false,"isSurahStart":false},{"surahNumber":50,"surahName":"سُورَةُ قٓ","surahEnglishName":"Qaaf","ayahNumber":31,"text":"وَأُزْلِفَتِ|And will be brought near|181|198|12980$ٱلْجَنَّةُ|the Paradise|102|137|6405$لِلْمُتَّقِينَ|to the righteous,|132|167|34$غَيْرَ|not|61|96|560$بَعِيدٍ|far.|60|77|1514$","juz":26,"ruku":454,"manzil":7,"hizbQuarter":208,"sajda":false,"isSurahStart":false},{"surahNumber":50,"surahName":"سُورَةُ قٓ","surahEnglishName":"Qaaf","ayahNumber":32,"text":"هَـٰذَا|`This|59|65|248$مَا|(is) what|80|92|262$تُوعَدُونَ|you were promised,|149|161|6059$لِكُلِّ|for everyone|104|116|3746$أَوَّابٍ|who turns|86|98|16084$حَفِيظٍ|(and) who keeps,|136|142|16085$","juz":26,"ruku":454,"manzil":7,"hizbQuarter":208,"sajda":false,"isSurahStart":false},{"surahNumber":50,"surahName":"سُورَةُ قٓ","surahEnglishName":"Qaaf","ayahNumber":33,"text":"مَّنْ|Who|50|66|76$خَشِىَ|feared|73|105|3914$ٱلرَّحْمَـٰنَ|the Most Gracious|140|172|10589$بِٱلْغَيْبِ|in the unseen,|115|147|36$وَجَآءَ|and came|84|116|7815$بِقَلْبٍ|with a heart|101|117|12978$مُّنِيبٍ|returning.|84|84|14205$","juz":26,"ruku":454,"manzil":7,"hizbQuarter":208,"sajda":false,"isSurahStart":false},{"surahNumber":50,"surahName":"سُورَةُ قٓ","surahEnglishName":"Qaaf","ayahNumber":34,"text":"ٱدْخُلُوهَا|Enter it|97|126|9786$بِسَلَـٰمٍ‌ۖ|in peace.|81|139|8528$ذَٲلِكَ|That|64|122|28$يَوْمُ|(is) a Day|85|143|5399$ٱلْخُلُودِ|(of) Eternity.`|115|144|16086$","juz":26,"ruku":454,"manzil":7,"hizbQuarter":208,"sajda":false,"isSurahStart":false},{"surahNumber":50,"surahName":"سُورَةُ قٓ","surahEnglishName":"Qaaf","ayahNumber":35,"text":"لَهُم|For them|79|96|98$مَّا|whatever|82|116|262$يَشَآءُونَ|they wish|96|130|9951$فِيهَا|therein|66|100|253$وَلَدَيْنَا|and with Us|98|132|12322$مَزِيدٌ|(is) more.|84|101|16087$","juz":26,"ruku":454,"manzil":7,"hizbQuarter":208,"sajda":false,"isSurahStart":false}]}