{"page":585,"ayahs":[{"surahNumber":80,"surahName":"سُورَةُ عَبَسَ","surahEnglishName":"Abasa","ayahNumber":1,"text":"بسم الله الرحمن الرحيم عبس وتولى","juz":30,"ruku":522,"manzil":7,"hizbQuarter":234,"sajda":false,"isSurahStart":false},{"surahNumber":80,"surahName":"سُورَةُ عَبَسَ","surahEnglishName":"Abasa","ayahNumber":2,"text":"أن جاءه الأعمى","juz":30,"ruku":522,"manzil":7,"hizbQuarter":234,"sajda":false,"isSurahStart":false},{"surahNumber":80,"surahName":"سُورَةُ عَبَسَ","surahEnglishName":"Abasa","ayahNumber":3,"text":"وما يدريك لعله يزكى","juz":30,"ruku":522,"manzil":7,"hizbQuarter":234,"sajda":false,"isSurahStart":false},{"surahNumber":80,"surahName":"سُورَةُ عَبَسَ","surahEnglishName":"Abasa","ayahNumber":4,"text":"أو يذكر فتنفعه الذكرى","juz":30,"ruku":522,"manzil":7,"hizbQuarter":234,"sajda":false,"isSurahStart":false},{"surahNumber":80,"surahName":"سُورَةُ عَبَسَ","surahEnglishName":"Abasa","ayahNumber":5,"text":"أما من استغنى","juz":30,"ruku":522,"manzil":7,"hizbQuarter":234,"sajda":false,"isSurahStart":false},{"surahNumber":80,"surahName":"سُورَةُ عَبَسَ","surahEnglishName":"Abasa","ayahNumber":6,"text":"فأنت له تصدى","juz":30,"ruku":522,"manzil":7,"hizbQuarter":234,"sajda":false,"isSurahStart":false},{"surahNumber":80,"surahName":"سُورَةُ عَبَسَ","surahEnglishName":"Abasa","ayahNumber":7,"text":"وما عليك ألا يزكى","juz":30,"ruku":522,"manzil":7,"hizbQuarter":234,"sajda":false,"isSurahStart":false},{"surahNumber":80,"surahName":"سُورَةُ عَبَسَ","surahEnglishName":"Abasa","ayahNumber":8,"text":"وأما من جاءك يسعى","juz":30,"ruku":522,"manzil":7,"hizbQuarter":234,"sajda":false,"isSurahStart":false},{"surahNumber":80,"surahName":"سُورَةُ عَبَسَ","surahEnglishName":"Abasa","ayahNumber":9,"text":"وهو يخشى","juz":30,"ruku":522,"manzil":7,"hizbQuarter":234,"sajda":false,"isSurahStart":false},{"surahNumber":80,"surahName":"سُورَةُ عَبَسَ","surahEnglishName":"Abasa","ayahNumber":10,"text":"فأنت عنه تلهى","juz":30,"ruku":522,"manzil":7,"hizbQuarter":234,"sajda":false,"isSurahStart":false},{"surahNumber":80,"surahName":"سُورَةُ عَبَسَ","surahEnglishName":"Abasa","ayahNumber":11,"text":"كلا إنها تذكرة","juz":30,"ruku":522,"manzil":7,"hizbQuarter":234,"sajda":false,"isSurahStart":false},{"surahNumber":80,"surahName":"سُورَةُ عَبَسَ","surahEnglishName":"Abasa","ayahNumber":12,"text":"فمن شاء ذكره","juz":30,"ruku":522,"manzil":7,"hizbQuarter":234,"sajda":false,"isSurahStart":false},{"surahNumber":80,"surahName":"سُورَةُ عَبَسَ","surahEnglishName":"Abasa","ayahNumber":13,"text":"في صحف مكرمة","juz":30,"ruku":522,"manzil":7,"hizbQuarter":234,"sajda":false,"isSurahStart":false},{"surahNumber":80,"surahName":"سُورَةُ عَبَسَ","surahEnglishName":"Abasa","ayahNumber":14,"text":"مرفوعة مطهرة","juz":30,"ruku":522,"manzil":7,"hizbQuarter":234,"sajda":false,"isSurahStart":false},{"surahNumber":80,"surahName":"سُورَةُ عَبَسَ","surahEnglishName":"Abasa","ayahNumber":15,"text":"بأيدي سفرة","juz":30,"ruku":522,"manzil":7,"hizbQuarter":234,"sajda":false,"isSurahStart":false},{"surahNumber":80,"surahName":"سُورَةُ عَبَسَ","surahEnglishName":"Abasa","ayahNumber":16,"text":"كرام بررة","juz":30,"ruku":522,"manzil":7,"hizbQuarter":234,"sajda":false,"isSurahStart":false},{"surahNumber":80,"surahName":"سُورَةُ عَبَسَ","surahEnglishName":"Abasa","ayahNumber":17,"text":"قتل الإنسان ما أكفره","juz":30,"ruku":522,"manzil":7,"hizbQuarter":234,"sajda":false,"isSurahStart":false},{"surahNumber":80,"surahName":"سُورَةُ عَبَسَ","surahEnglishName":"Abasa","ayahNumber":18,"text":"من أي شيء خلقه","juz":30,"ruku":522,"manzil":7,"hizbQuarter":234,"sajda":false,"isSurahStart":false},{"surahNumber":80,"surahName":"سُورَةُ عَبَسَ","surahEnglishName":"Abasa","ayahNumber":19,"text":"من نطفة خلقه فقدره","juz":30,"ruku":522,"manzil":7,"hizbQuarter":234,"sajda":false,"isSurahStart":false},{"surahNumber":80,"surahName":"سُورَةُ عَبَسَ","surahEnglishName":"Abasa","ayahNumber":20,"text":"ثم السبيل يسره","juz":30,"ruku":522,"manzil":7,"hizbQuarter":234,"sajda":false,"isSurahStart":false},{"surahNumber":80,"surahName":"سُورَةُ عَبَسَ","surahEnglishName":"Abasa","ayahNumber":21,"text":"ثم أماته فأقبره","juz":30,"ruku":522,"manzil":7,"hizbQuarter":234,"sajda":false,"isSurahStart":false},{"surahNumber":80,"surahName":"سُورَةُ عَبَسَ","surahEnglishName":"Abasa","ayahNumber":22,"text":"ثم إذا شاء أنشره","juz":30,"ruku":522,"manzil":7,"hizbQuarter":234,"sajda":false,"isSurahStart":false},{"surahNumber":80,"surahName":"سُورَةُ عَبَسَ","surahEnglishName":"Abasa","ayahNumber":23,"text":"كلا لما يقض ما أمره","juz":30,"ruku":522,"manzil":7,"hizbQuarter":234,"sajda":false,"isSurahStart":false},{"surahNumber":80,"surahName":"سُورَةُ عَبَسَ","surahEnglishName":"Abasa","ayahNumber":24,"text":"فلينظر الإنسان إلى طعامه","juz":30,"ruku":522,"manzil":7,"hizbQuarter":234,"sajda":false,"isSurahStart":false},{"surahNumber":80,"surahName":"سُورَةُ عَبَسَ","surahEnglishName":"Abasa","ayahNumber":25,"text":"أنا صببنا الماء صبا","juz":30,"ruku":522,"manzil":7,"hizbQuarter":234,"sajda":false,"isSurahStart":false},{"surahNumber":80,"surahName":"سُورَةُ عَبَسَ","surahEnglishName":"Abasa","ayahNumber":26,"text":"ثم شققنا الأرض شقا","juz":30,"ruku":522,"manzil":7,"hizbQuarter":234,"sajda":false,"isSurahStart":false},{"surahNumber":80,"surahName":"سُورَةُ عَبَسَ","surahEnglishName":"Abasa","ayahNumber":27,"text":"فأنبتنا فيها حبا","juz":30,"ruku":522,"manzil":7,"hizbQuarter":234,"sajda":false,"isSurahStart":false},{"surahNumber":80,"surahName":"سُورَةُ عَبَسَ","surahEnglishName":"Abasa","ayahNumber":28,"text":"وعنبا وقضبا","juz":30,"ruku":522,"manzil":7,"hizbQuarter":234,"sajda":false,"isSurahStart":false},{"surahNumber":80,"surahName":"سُورَةُ عَبَسَ","surahEnglishName":"Abasa","ayahNumber":29,"text":"وزيتونا ونخلا","juz":30,"ruku":522,"manzil":7,"hizbQuarter":234,"sajda":false,"isSurahStart":false},{"surahNumber":80,"surahName":"سُورَةُ عَبَسَ","surahEnglishName":"Abasa","ayahNumber":30,"text":"وحدائق غلبا","juz":30,"ruku":522,"manzil":7,"hizbQuarter":234,"sajda":false,"isSurahStart":false},{"surahNumber":80,"surahName":"سُورَةُ عَبَسَ","surahEnglishName":"Abasa","ayahNumber":31,"text":"وفاكهة وأبا","juz":30,"ruku":522,"manzil":7,"hizbQuarter":234,"sajda":false,"isSurahStart":false},{"surahNumber":80,"surahName":"سُورَةُ عَبَسَ","surahEnglishName":"Abasa","ayahNumber":32,"text":"متاعا لكم ولأنعامكم","juz":30,"ruku":522,"manzil":7,"hizbQuarter":234,"sajda":false,"isSurahStart":false},{"surahNumber":80,"surahName":"سُورَةُ عَبَسَ","surahEnglishName":"Abasa","ayahNumber":33,"text":"فإذا جاءت الصاخة","juz":30,"ruku":522,"manzil":7,"hizbQuarter":234,"sajda":false,"isSurahStart":false},{"surahNumber":80,"surahName":"سُورَةُ عَبَسَ","surahEnglishName":"Abasa","ayahNumber":34,"text":"يوم يفر المرء من أخيه","juz":30,"ruku":522,"manzil":7,"hizbQuarter":234,"sajda":false,"isSurahStart":false},{"surahNumber":80,"surahName":"سُورَةُ عَبَسَ","surahEnglishName":"Abasa","ayahNumber":35,"text":"وأمه وأبيه","juz":30,"ruku":522,"manzil":7,"hizbQuarter":234,"sajda":false,"isSurahStart":false},{"surahNumber":80,"surahName":"سُورَةُ عَبَسَ","surahEnglishName":"Abasa","ayahNumber":36,"text":"وصاحبته وبنيه","juz":30,"ruku":522,"manzil":7,"hizbQuarter":234,"sajda":false,"isSurahStart":false},{"surahNumber":80,"surahName":"سُورَةُ عَبَسَ","surahEnglishName":"Abasa","ayahNumber":37,"text":"لكل امرئ منهم يومئذ شأن يغنيه","juz":30,"ruku":522,"manzil":7,"hizbQuarter":234,"sajda":false,"isSurahStart":false},{"surahNumber":80,"surahName":"سُورَةُ عَبَسَ","surahEnglishName":"Abasa","ayahNumber":38,"text":"وجوه يومئذ مسفرة","juz":30,"ruku":522,"manzil":7,"hizbQuarter":234,"sajda":false,"isSurahStart":false},{"surahNumber":80,"surahName":"سُورَةُ عَبَسَ","surahEnglishName":"Abasa","ayahNumber":39,"text":"ضاحكة مستبشرة","juz":30,"ruku":522,"manzil":7,"hizbQuarter":234,"sajda":false,"isSurahStart":false},{"surahNumber":80,"surahName":"سُورَةُ عَبَسَ","surahEnglishName":"Abasa","ayahNumber":40,"text":"ووجوه يومئذ عليها غبرة","juz":30,"ruku":522,"manzil":7,"hizbQuarter":234,"sajda":false,"isSurahStart":false},{"surahNumber":80,"surahName":"سُورَةُ عَبَسَ","surahEnglishName":"Abasa","ayahNumber":41,"text":"ترهقها قترة","juz":30,"ruku":522,"manzil":7,"hizbQuarter":234,"sajda":false,"isSurahStart":false},{"surahNumber":80,"surahName":"سُورَةُ عَبَسَ","surahEnglishName":"Abasa","ayahNumber":42,"text":"أولئك هم الكفرة الفجرة","juz":30,"ruku":522,"manzil":7,"hizbQuarter":234,"sajda":false,"isSurahStart":false}]}