{"page":581,"ayahs":[{"surahNumber":77,"surahName":"سُورَةُ المُرۡسَلَاتِ","surahEnglishName":"Al-Mursalaat","ayahNumber":20,"text":"أَلَمْ|Did not|67|101|348$نَخْلُقكُّم|We create you|118|186|17720$مِّن|from|50|118|53$مَّآءٍ|a water|71|139|9562$مَّهِينٍ|despicable?|96|130|13874$","juz":29,"ruku":516,"manzil":7,"hizbQuarter":232,"sajda":false,"isSurahStart":false},{"surahNumber":77,"surahName":"سُورَةُ المُرۡسَلَاتِ","surahEnglishName":"Al-Mursalaat","ayahNumber":21,"text":"فَجَعَلْنَـٰهُ|Then We placed it|141|197|12739$فِى|in|48|159|89$قَرَارٍ|an abode|81|192|9608$مَّكِينٍ|safe|71|127|12225$","juz":29,"ruku":516,"manzil":7,"hizbQuarter":232,"sajda":false,"isSurahStart":false},{"surahNumber":77,"surahName":"سُورَةُ المُرۡسَلَاتِ","surahEnglishName":"Al-Mursalaat","ayahNumber":22,"text":"إِلَىٰ|For|53|171|118$قَدَرٍ|a period|73|308|11439$مَّعْلُومٍ|known.|78|196|9742$","juz":29,"ruku":516,"manzil":7,"hizbQuarter":232,"sajda":false,"isSurahStart":false},{"surahNumber":77,"surahName":"سُورَةُ المُرۡسَلَاتِ","surahEnglishName":"Al-Mursalaat","ayahNumber":23,"text":"فَقَدَرْنَا|So We measured,|136|210|17721$فَنِعْمَ|and Best|78|227|9441$ٱلْقَـٰدِرُونَ|(are We to) measure!|163|238|17722$","juz":29,"ruku":516,"manzil":7,"hizbQuarter":232,"sajda":false,"isSurahStart":false},{"surahNumber":77,"surahName":"سُورَةُ المُرۡسَلَاتِ","surahEnglishName":"Al-Mursalaat","ayahNumber":24,"text":"وَيْلٌ|Woe|58|163|15631$يَوْمَئِذٍ|that Day|78|288|3485$لِّلْمُكَذِّبِينَ|to the deniers.|118|223|16185$","juz":29,"ruku":516,"manzil":7,"hizbQuarter":232,"sajda":false,"isSurahStart":false},{"surahNumber":77,"surahName":"سُورَةُ المُرۡسَلَاتِ","surahEnglishName":"Al-Mursalaat","ayahNumber":25,"text":"أَلَمْ|Have not|80|133|348$نَجْعَلِ|We made|81|187|17723$ٱلْأَرْضَ|the earth|92|198|197$كِفَاتًا|a receptacle|103|156|17724$","juz":29,"ruku":516,"manzil":7,"hizbQuarter":232,"sajda":false,"isSurahStart":false},{"surahNumber":77,"surahName":"سُورَةُ المُرۡسَلَاتِ","surahEnglishName":"Al-Mursalaat","ayahNumber":26,"text":"أَحْيَآءً|(For the) living|118|334|17725$وَأَمْوَٲتًا|and (the) dead,|125|341|17726$","juz":29,"ruku":516,"manzil":7,"hizbQuarter":232,"sajda":false,"isSurahStart":false},{"surahNumber":77,"surahName":"سُورَةُ المُرۡسَلَاتِ","surahEnglishName":"Al-Mursalaat","ayahNumber":27,"text":"وَجَعَلْنَا|And We made|111|124|4805$فِيهَا|therein|66|91|253$رَوَٲسِىَ|firmly set mountains|153|178|9319$شَـٰمِخَـٰتٍ|lofty,|104|129|17727$وَأَسْقَيْنَـٰكُم|and We gave you to drink|191|204|17728$مَّآءً|water -|70|339|202$فُرَاتًا|sweet?|67|336|17729$","juz":29,"ruku":516,"manzil":7,"hizbQuarter":232,"sajda":false,"isSurahStart":false},{"surahNumber":77,"surahName":"سُورَةُ المُرۡسَلَاتِ","surahEnglishName":"Al-Mursalaat","ayahNumber":28,"text":"وَيْلٌ|Woe|58|163|15631$يَوْمَئِذٍ|that Day|78|288|3485$لِّلْمُكَذِّبِينَ|to the deniers.|118|223|16185$","juz":29,"ruku":516,"manzil":7,"hizbQuarter":232,"sajda":false,"isSurahStart":false},{"surahNumber":77,"surahName":"سُورَةُ المُرۡسَلَاتِ","surahEnglishName":"Al-Mursalaat","ayahNumber":29,"text":"ٱنطَلِقُوٓاْ|`Proceed|90|116|17730$إِلَىٰ|to|53|104|118$مَا|what|53|104|262$كُنتُم|you used|80|131|214$بِهِۦ|in it|52|103|204$تُكَذِّبُونَ|(to) deny,|91|117|13899$","juz":29,"ruku":516,"manzil":7,"hizbQuarter":232,"sajda":false,"isSurahStart":false},{"surahNumber":77,"surahName":"سُورَةُ المُرۡسَلَاتِ","surahEnglishName":"Al-Mursalaat","ayahNumber":30,"text":"ٱنطَلِقُوٓاْ|Proceed|90|124|17730$إِلَىٰ|to|53|121|118$ظِلٍّ|a shadow|83|151|17731$ذِى ثَلَـٰثِ|having three|105|173|17732$شُعَبٍ|columns|73|107|17733$","juz":29,"ruku":516,"manzil":7,"hizbQuarter":232,"sajda":false,"isSurahStart":false},{"surahNumber":77,"surahName":"سُورَةُ المُرۡسَلَاتِ","surahEnglishName":"Al-Mursalaat","ayahNumber":31,"text":"لَّا|No|37|62|30$ظَلِيلٍ|cool shade|91|141|17734$وَلَا|and not|71|121|25$يُغْنِى|availing|69|119|8150$مِنَ|against|68|118|156$ٱللَّهَبِ|the flame.|87|112|17735$","juz":29,"ruku":516,"manzil":7,"hizbQuarter":232,"sajda":false,"isSurahStart":false},{"surahNumber":77,"surahName":"سُورَةُ المُرۡسَلَاتِ","surahEnglishName":"Al-Mursalaat","ayahNumber":32,"text":"إِنَّهَا|Indeed, it|84|135|666$تَرْمِى|throws up|86|188|17736$بِشَرَرٍ|sparks|77|179|17737$كَٱلْقَصْرِ|as the fortress,|123|174|17738$","juz":29,"ruku":516,"manzil":7,"hizbQuarter":232,"sajda":false,"isSurahStart":false},{"surahNumber":77,"surahName":"سُورَةُ المُرۡسَلَاتِ","surahEnglishName":"Al-Mursalaat","ayahNumber":33,"text":"كَأَنَّهُۥ|As if they (were)|133|228|6983$جِمَـٰلَتٌ|camels|87|278|17739$صُفْرٌ|yellow.`|74|169|17740$","juz":29,"ruku":516,"manzil":7,"hizbQuarter":232,"sajda":false,"isSurahStart":false},{"surahNumber":77,"surahName":"سُورَةُ المُرۡسَلَاتِ","surahEnglishName":"Al-Mursalaat","ayahNumber":34,"text":"وَيْلٌ|Woe|58|163|15631$يَوْمَئِذٍ|that Day|78|288|3485$لِّلْمُكَذِّبِينَ|to the deniers.|118|223|16185$","juz":29,"ruku":516,"manzil":7,"hizbQuarter":232,"sajda":false,"isSurahStart":false},{"surahNumber":77,"surahName":"سُورَةُ المُرۡسَلَاتِ","surahEnglishName":"Al-Mursalaat","ayahNumber":35,"text":"هَـٰذَا|This|59|120|248$يَوْمُ|(is) a Day|85|207|5399$لَا|not|42|164|30$يَنطِقُونَ|they will speak,|123|184|11840$","juz":29,"ruku":516,"manzil":7,"hizbQuarter":232,"sajda":false,"isSurahStart":false},{"surahNumber":77,"surahName":"سُورَةُ المُرۡسَلَاتِ","surahEnglishName":"Al-Mursalaat","ayahNumber":36,"text":"وَلَا|And not|72|113|25$يُؤْذَنُ|will it be permitted|143|226|10096$لَهُمْ|for them|76|159|98$فَيَعْتَذِرُونَ|to make excuses.|136|177|17741$","juz":29,"ruku":516,"manzil":7,"hizbQuarter":232,"sajda":false,"isSurahStart":false},{"surahNumber":77,"surahName":"سُورَةُ المُرۡسَلَاتِ","surahEnglishName":"Al-Mursalaat","ayahNumber":37,"text":"وَيْلٌ|Woe|58|163|15631$يَوْمَئِذٍ|that Day|78|288|3485$لِّلْمُكَذِّبِينَ|to the deniers.|118|223|16185$","juz":29,"ruku":516,"manzil":7,"hizbQuarter":232,"sajda":false,"isSurahStart":false},{"surahNumber":77,"surahName":"سُورَةُ المُرۡسَلَاتِ","surahEnglishName":"Al-Mursalaat","ayahNumber":38,"text":"هَـٰذَا|This|59|105|248$يَوْمُ|(is the) Day|99|191|5399$ٱلْفَصْلِ‌ۖ|(of) Judgment;|119|211|14586$جَمَعْنَـٰكُمْ|We have gathered you|171|217|17742$وَٱلْأَوَّلِينَ|and the former (people).|183|183|17743$","juz":29,"ruku":516,"manzil":7,"hizbQuarter":232,"sajda":false,"isSurahStart":false},{"surahNumber":77,"surahName":"سُورَةُ المُرۡسَلَاتِ","surahEnglishName":"Al-Mursalaat","ayahNumber":39,"text":"فَإِن|So if|53|87|227$كَانَ|is|57|124|913$لَكُمْ|for you|67|134|207$كَيْدٌ|a plan,|65|132|17744$فَكِيدُونِ|then plan against Me.|164|198|17745$","juz":29,"ruku":516,"manzil":7,"hizbQuarter":232,"sajda":false,"isSurahStart":false},{"surahNumber":77,"surahName":"سُورَةُ المُرۡسَلَاتِ","surahEnglishName":"Al-Mursalaat","ayahNumber":40,"text":"وَيْلٌ|Woe|58|163|15631$يَوْمَئِذٍ|that Day|78|288|3485$لِّلْمُكَذِّبِينَ|to the deniers.|118|223|16185$","juz":29,"ruku":516,"manzil":7,"hizbQuarter":232,"sajda":false,"isSurahStart":false},{"surahNumber":77,"surahName":"سُورَةُ المُرۡسَلَاتِ","surahEnglishName":"Al-Mursalaat","ayahNumber":41,"text":"إِنَّ|Indeed,|70|100|58$ٱلْمُتَّقِينَ|the righteous|108|168|1567$فِى|(will be) in|89|149|89$ظِلَـٰلٍ|shades|69|129|14516$وَعُيُونٍ|and springs,|100|130|9785$","juz":29,"ruku":517,"manzil":7,"hizbQuarter":232,"sajda":false,"isSurahStart":false},{"surahNumber":77,"surahName":"سُورَةُ المُرۡسَلَاتِ","surahEnglishName":"Al-Mursalaat","ayahNumber":42,"text":"وَفَوَٲكِهَ|And fruits|89|189|17746$مِمَّا|from what|87|287|216$يَشْتَهُونَ|they desire.|99|199|9997$","juz":29,"ruku":517,"manzil":7,"hizbQuarter":232,"sajda":false,"isSurahStart":false},{"surahNumber":77,"surahName":"سُورَةُ المُرۡسَلَاتِ","surahEnglishName":"Al-Mursalaat","ayahNumber":43,"text":"كُلُواْ|`Eat|61|75|539$وَٱشْرَبُواْ|and drink|103|131|578$هَنِيٓـــَٔۢا|(in) satisfaction|125|153|16191$بِمَا|for what|76|104|43$كُنتُمْ|you used|80|108|214$تَعْمَلُونَ|(to) do.`|92|106|725$","juz":29,"ruku":517,"manzil":7,"hizbQuarter":232,"sajda":false,"isSurahStart":false},{"surahNumber":77,"surahName":"سُورَةُ المُرۡسَلَاتِ","surahEnglishName":"Al-Mursalaat","ayahNumber":44,"text":"إِنَّا|Indeed, We|96|145|120$كَذَٲلِكَ|thus|77|175|702$نَجْزِى|reward|81|179|5793$ٱلْمُحْسِنِينَ|the good-doers.|127|176|556$","juz":29,"ruku":517,"manzil":7,"hizbQuarter":232,"sajda":false,"isSurahStart":false},{"surahNumber":77,"surahName":"سُورَةُ المُرۡسَلَاتِ","surahEnglishName":"Al-Mursalaat","ayahNumber":45,"text":"وَيْلٌ|Woe|58|163|15631$يَوْمَئِذٍ|that Day|78|288|3485$لِّلْمُكَذِّبِينَ|to the deniers.|118|223|16185$","juz":29,"ruku":517,"manzil":7,"hizbQuarter":232,"sajda":false,"isSurahStart":false},{"surahNumber":77,"surahName":"سُورَةُ المُرۡسَلَاتِ","surahEnglishName":"Al-Mursalaat","ayahNumber":46,"text":"كُلُواْ|Eat|61|82|539$وَتَمَتَّعُواْ|and enjoy yourselves|160|202|17747$قَلِيلاً|a little;|68|110|433$إِنَّكُم|indeed, you|97|140|514$مُّجْرِمُونَ|(are) criminals.|119|140|15591$","juz":29,"ruku":517,"manzil":7,"hizbQuarter":232,"sajda":false,"isSurahStart":false},{"surahNumber":77,"surahName":"سُورَةُ المُرۡسَلَاتِ","surahEnglishName":"Al-Mursalaat","ayahNumber":47,"text":"وَيْلٌ|Woe|58|163|15631$يَوْمَئِذٍ|that Day|78|288|3485$لِّلْمُكَذِّبِينَ|to the deniers.|118|223|16185$","juz":29,"ruku":517,"manzil":7,"hizbQuarter":232,"sajda":false,"isSurahStart":false},{"surahNumber":77,"surahName":"سُورَةُ المُرۡسَلَاتِ","surahEnglishName":"Al-Mursalaat","ayahNumber":48,"text":"وَإِذَا|And when|85|106|96$قِيلَ|it is said|75|116|97$لَهُمُ|to them,|77|118|1027$ٱرْكَعُواْ|`Bow`,|90|131|12199$لَا|not|42|83|30$يَرْكَعُونَ|they bow.|101|122|17748$","juz":29,"ruku":517,"manzil":7,"hizbQuarter":232,"sajda":false,"isSurahStart":false},{"surahNumber":77,"surahName":"سُورَةُ المُرۡسَلَاتِ","surahEnglishName":"Al-Mursalaat","ayahNumber":49,"text":"وَيْلٌ|Woe|58|163|15631$يَوْمَئِذٍ|that Day|78|288|3485$لِّلْمُكَذِّبِينَ|to the deniers.|118|223|16185$","juz":29,"ruku":517,"manzil":7,"hizbQuarter":232,"sajda":false,"isSurahStart":false},{"surahNumber":77,"surahName":"سُورَةُ المُرۡسَلَاتِ","surahEnglishName":"Al-Mursalaat","ayahNumber":50,"text":"فَبِأَىِّ|Then in what|107|152|7041$حَدِيثِۭ|statement|88|178|4559$بَعْدَهُۥ|after it|76|166|7042$يُؤْمِنُونَ|will they believe?|133|178|35$","juz":29,"ruku":517,"manzil":7,"hizbQuarter":232,"sajda":false,"isSurahStart":false}]}