{"page":145,"ayahs":[{"surahNumber":6,"surahName":"سُورَةُ الأَنۡعَامِ","surahEnglishName":"Al-An'aam","ayahNumber":132,"text":"وَلِكُلٍّ دَرَجٰتٌ مِمّا عَمِلوا ۚ وَما رَبُّكَ بِغٰفِلٍ عَمّا يَعمَلونَ","juz":8,"ruku":117,"manzil":2,"hizbQuarter":58,"sajda":false,"isSurahStart":false},{"surahNumber":6,"surahName":"سُورَةُ الأَنۡعَامِ","surahEnglishName":"Al-An'aam","ayahNumber":133,"text":"وَرَبُّكَ الغَنِىُّ ذُو الرَّحمَةِ ۚ إِن يَشَأ يُذهِبكُم وَيَستَخلِف مِن بَعدِكُم ما يَشاءُ كَما أَنشَأَكُم مِن ذُرِّيَّةِ قَومٍ ءاخَرينَ","juz":8,"ruku":117,"manzil":2,"hizbQuarter":58,"sajda":false,"isSurahStart":false},{"surahNumber":6,"surahName":"سُورَةُ الأَنۡعَامِ","surahEnglishName":"Al-An'aam","ayahNumber":134,"text":"إِنَّ ما توعَدونَ لَءاتٍ ۖ وَما أَنتُم بِمُعجِزينَ","juz":8,"ruku":117,"manzil":2,"hizbQuarter":58,"sajda":false,"isSurahStart":false},{"surahNumber":6,"surahName":"سُورَةُ الأَنۡعَامِ","surahEnglishName":"Al-An'aam","ayahNumber":135,"text":"قُل يٰقَومِ اعمَلوا عَلىٰ مَكانَتِكُم إِنّى عامِلٌ ۖ فَسَوفَ تَعلَمونَ مَن تَكونُ لَهُ عٰقِبَةُ الدّارِ ۗ إِنَّهُ لا يُفلِحُ الظّٰلِمونَ","juz":8,"ruku":117,"manzil":2,"hizbQuarter":58,"sajda":false,"isSurahStart":false},{"surahNumber":6,"surahName":"سُورَةُ الأَنۡعَامِ","surahEnglishName":"Al-An'aam","ayahNumber":136,"text":"وَجَعَلوا لِلَّهِ مِمّا ذَرَأَ مِنَ الحَرثِ وَالأَنعٰمِ نَصيبًا فَقالوا هٰذا لِلَّهِ بِزَعمِهِم وَهٰذا لِشُرَكائِنا ۖ فَما كانَ لِشُرَكائِهِم فَلا يَصِلُ إِلَى اللَّهِ ۖ وَما كانَ لِلَّهِ فَهُوَ يَصِلُ إِلىٰ شُرَكائِهِم ۗ ساءَ ما يَحكُمونَ","juz":8,"ruku":117,"manzil":2,"hizbQuarter":58,"sajda":false,"isSurahStart":false},{"surahNumber":6,"surahName":"سُورَةُ الأَنۡعَامِ","surahEnglishName":"Al-An'aam","ayahNumber":137,"text":"وَكَذٰلِكَ زَيَّنَ لِكَثيرٍ مِنَ المُشرِكينَ قَتلَ أَولٰدِهِم شُرَكاؤُهُم لِيُردوهُم وَلِيَلبِسوا عَلَيهِم دينَهُم ۖ وَلَو شاءَ اللَّهُ ما فَعَلوهُ ۖ فَذَرهُم وَما يَفتَرونَ","juz":8,"ruku":117,"manzil":2,"hizbQuarter":58,"sajda":false,"isSurahStart":false}]}