{"page":566,"ayahs":[{"surahNumber":68,"surahName":"سُورَةُ القَلَمِ","surahEnglishName":"Al-Qalam","ayahNumber":43,"text":"خَ[n[ـٰ]شِعَةً أَ[q:4718[بْ]صَ[n[ـٰ]رُهُمْ تَرْهَقُهُمْ ذِلَّ[a:13846[ةٌ‌ۖ و]َقَ[q:387[دْ] كَانُو[s[اْ] يُ[q:1815[دْ]عَوْنَ إِلَى [h:13845[ٱ][l[ل]سُّجُودِ وَهُمْ سَ[n[ـٰ]لِم[p[ُو]نَ","juz":29,"ruku":499,"manzil":7,"hizbQuarter":226,"sajda":false,"isSurahStart":false},{"surahNumber":68,"surahName":"سُورَةُ القَلَمِ","surahEnglishName":"Al-Qalam","ayahNumber":44,"text":"فَذَرْنِى وَم[a:13847[َن ي]ُكَذِّبُ بِهَ[n[ـٰ]ذَا [h:7957[ٱ]لْحَدِيثِ‌ۖ سَنَسْتَ[q:5160[دْ]رِجُه[w:5161[ُم م]ِّنْ حَيْثُ لَا يَعْلَم[p[ُو]نَ","juz":29,"ruku":499,"manzil":7,"hizbQuarter":226,"sajda":false,"isSurahStart":false},{"surahNumber":68,"surahName":"سُورَةُ القَلَمِ","surahEnglishName":"Al-Qalam","ayahNumber":45,"text":"وَأُمْلِى لَهُمْ‌ۚ إِ[g[نّ]َ كَيْدِى مَت[p[ِي]نٌ","juz":29,"ruku":499,"manzil":7,"hizbQuarter":226,"sajda":false,"isSurahStart":false},{"surahNumber":68,"surahName":"سُورَةُ القَلَمِ","surahEnglishName":"Al-Qalam","ayahNumber":46,"text":"أَمْ تَسْــَٔلُهُمْ أَ[q:2795[جْ][f:12943[رًا ف]َه[w:12944[ُم م]ّ[a:12945[ِن م]َّغْرَ[a:12946[مٍ م]ُّثْقَل[p[ُو]نَ","juz":29,"ruku":499,"manzil":7,"hizbQuarter":226,"sajda":false,"isSurahStart":false},{"surahNumber":68,"surahName":"سُورَةُ القَلَمِ","surahEnglishName":"Al-Qalam","ayahNumber":47,"text":"أَمْ عِ[f:3212[ند]َهُمُ [h:12947[ٱ]لْغَيْبُ فَهُمْ يَكْتُب[p[ُو]نَ","juz":29,"ruku":499,"manzil":7,"hizbQuarter":226,"sajda":false,"isSurahStart":false},{"surahNumber":68,"surahName":"سُورَةُ القَلَمِ","surahEnglishName":"Al-Qalam","ayahNumber":48,"text":"فَ[h:9999[ٱ]صْبِرْ لِحُكْمِ رَبِّكَ وَلَا تَكُ[f:13848[ن ك]َصَاحِبِ [h:13849[ٱ]لْحُوتِ إِذْ نَادَىٰ وَهُوَ مَكْظ[p[ُو]مٌ","juz":29,"ruku":499,"manzil":7,"hizbQuarter":226,"sajda":false,"isSurahStart":false},{"surahNumber":68,"surahName":"سُورَةُ القَلَمِ","surahEnglishName":"Al-Qalam","ayahNumber":49,"text":"لَّوْل[o[َآ] أَ[f:13850[ن ت]َد[n[َٲ]رَكَهُ[n[ۥ] نِعْمَ[a:13851[ةٌ م]ّ[u:192[ِن ر]َّبِّه[n[ِۦ] لَنُبِذَ بِ[h:11434[ٱ]لْعَر[o[َا]ٓءِ وَهُوَ مَذْم[p[ُو]مٌ","juz":29,"ruku":499,"manzil":7,"hizbQuarter":226,"sajda":false,"isSurahStart":false},{"surahNumber":68,"surahName":"سُورَةُ القَلَمِ","surahEnglishName":"Al-Qalam","ayahNumber":50,"text":"فَ[h:9999[ٱ][q:13852[جْ]تَبَ[n[ـٰ]هُ رَبُّهُ[n[ۥ] فَجَعَلَهُ[n[ۥ] مِنَ [h:1889[ٱ][l[ل]صَّ[n[ـٰ]لِح[p[ِي]نَ","juz":29,"ruku":499,"manzil":7,"hizbQuarter":226,"sajda":false,"isSurahStart":false},{"surahNumber":68,"surahName":"سُورَةُ القَلَمِ","surahEnglishName":"Al-Qalam","ayahNumber":51,"text":"وَإ[a:13853[ِن ي]َكَادُ [h:13854[ٱ]لَّذِينَ كَفَرُو[s[اْ] لَيُزْلِقُونَكَ بِأَ[q:13855[بْ]صَ[n[ـٰ]رِهِمْ لَ[g[مّ]َا سَمِعُو[s[اْ] [h:13856[ٱ][l[ل]ذِّكْرَ وَيَقُولُونَ إِ[g[نّ]َهُ[n[ۥ] لَمَ[q:7198[جْ]ن[p[ُو]نٌ","juz":29,"ruku":499,"manzil":7,"hizbQuarter":226,"sajda":false,"isSurahStart":false},{"surahNumber":68,"surahName":"سُورَةُ القَلَمِ","surahEnglishName":"Al-Qalam","ayahNumber":52,"text":"وَمَا هُوَ إِلَّا ذِكْ[u:6839[رٌ ل]ِّلْعَ[n[ـٰ]لَم[p[ِي]نَ","juz":29,"ruku":499,"manzil":7,"hizbQuarter":226,"sajda":false,"isSurahStart":false},{"surahNumber":69,"surahName":"سُورَةُ الحَاقَّةِ","surahEnglishName":"Al-Haaqqa","ayahNumber":1,"text":"ٱلْح[m[َا]ٓقَّةُ","juz":29,"ruku":500,"manzil":7,"hizbQuarter":227,"sajda":false,"isSurahStart":false},{"surahNumber":69,"surahName":"سُورَةُ الحَاقَّةِ","surahEnglishName":"Al-Haaqqa","ayahNumber":2,"text":"مَا [h:13857[ٱ]لْح[m[َا]ٓقَّةُ","juz":29,"ruku":500,"manzil":7,"hizbQuarter":227,"sajda":false,"isSurahStart":false},{"surahNumber":69,"surahName":"سُورَةُ الحَاقَّةِ","surahEnglishName":"Al-Haaqqa","ayahNumber":3,"text":"وَم[o[َآ] أَ[q:13858[دْ]رَ[n[ٮٰ]كَ مَا [h:13857[ٱ]لْح[m[َا]ٓقَّةُ","juz":29,"ruku":500,"manzil":7,"hizbQuarter":227,"sajda":false,"isSurahStart":false},{"surahNumber":69,"surahName":"سُورَةُ الحَاقَّةِ","surahEnglishName":"Al-Haaqqa","ayahNumber":4,"text":"كَذَّبَتْ ثَمُودُ وَعَا[i:13859[دُۢ ب]ِ[h:13860[ٱ]لْقَارِعَةِ","juz":29,"ruku":500,"manzil":7,"hizbQuarter":227,"sajda":false,"isSurahStart":false},{"surahNumber":69,"surahName":"سُورَةُ الحَاقَّةِ","surahEnglishName":"Al-Haaqqa","ayahNumber":5,"text":"فَأَ[g[مّ]َا ثَمُودُ فَأُهْلِكُو[s[اْ] بِ[h:13861[ٱ][l[ل]طَّاغِيَةِ","juz":29,"ruku":500,"manzil":7,"hizbQuarter":227,"sajda":false,"isSurahStart":false},{"surahNumber":69,"surahName":"سُورَةُ الحَاقَّةِ","surahEnglishName":"Al-Haaqqa","ayahNumber":6,"text":"وَأَ[g[مّ]َا عَا[f:13862[دٌ ف]َأُهْلِكُو[s[اْ] بِرِي[f:13863[حٍ ص]َرْصَرٍ عَاتِيَةٍ","juz":29,"ruku":500,"manzil":7,"hizbQuarter":227,"sajda":false,"isSurahStart":false},{"surahNumber":69,"surahName":"سُورَةُ الحَاقَّةِ","surahEnglishName":"Al-Haaqqa","ayahNumber":7,"text":"سَخَّرَهَا عَلَيْهِمْ سَ[q:158[بْ]عَ لَيَا[a:13864[لٍ و]َثَمَ[n[ـٰ]نِيَةَ أَيَّامٍ حُسُو[f:13865[مًا ف]َتَرَى [h:13866[ٱ]لْقَوْمَ فِيهَا صَرْعَىٰ كَأَ[g[نّ]َهُمْ أَعْجَازُ نَخْلٍ خَاوِيَةٍ","juz":29,"ruku":500,"manzil":7,"hizbQuarter":227,"sajda":false,"isSurahStart":false},{"surahNumber":69,"surahName":"سُورَةُ الحَاقَّةِ","surahEnglishName":"Al-Haaqqa","ayahNumber":8,"text":"فَهَلْ تَرَىٰ لَه[w:1812[ُم م]ّ[i:13867[ِنۢ ب]َاقِيَةٍ","juz":29,"ruku":500,"manzil":7,"hizbQuarter":227,"sajda":false,"isSurahStart":false}]}