{"page":21,"ayahs":[{"surahNumber":2,"surahName":"سُورَةُ البَقَرَةِ","surahEnglishName":"Al-Baqara","ayahNumber":135,"text":"وَقَالُواْ|And they said,|116|123|760$كُونُواْ|`Be|76|89|645$هُودًا|Jews|66|79|1036$أَوْ|or|41|54|154$نَصَـٰرَىٰ|Christians,|98|111|1037$تَهْتَدُواْ‌ۗ|(then) you will be guided.`|198|211|1230$قُلْ|Say,|50|57|765$بَلْ|`Nay,|58|71|848$مِلَّةَ|(the) religion|105|132|1231$إِبْرَٲهِــۧمَ|(of) Ibrahim,|103|130|1127$حَنِيفًا‌ۖ|(the) upright;|111|138|1232$وَمَا|and not|71|98|46$كَانَ|he was|67|94|913$مِنَ|of|50|63|156$ٱلْمُشْرِكِينَ|those who associated partners (with Allah).`|319|319|990$","juz":1,"ruku":17,"manzil":1,"hizbQuarter":8,"sajda":false,"isSurahStart":false},{"surahNumber":2,"surahName":"سُورَةُ البَقَرَةِ","surahEnglishName":"Al-Baqara","ayahNumber":136,"text":"قُولُوٓاْ|Say,|71|81|1233$ءَامَنَّا|`We have believed|145|165|78$بِٱللَّهِ|in Allah|67|87|79$وَمَآ|and what|82|102|46$أُنزِلَ|(is) revealed|103|123|44$إِلَيْنَا|to us|57|77|1234$وَمَآ|and what|82|92|46$أُنزِلَ|was revealed|107|123|44$إِلَىٰٓ|to|53|85|118$إِبْرَٲهِــۧمَ|Ibrahim|90|122|1127$وَإِسْمَـٰعِيلَ|and Ismail|115|147|1145$وَإِسْحَـٰقَ|and Ishaq|101|133|1221$وَيَعْقُوبَ|and Yaqub|100|116|1235$وَٱلْأَسْبَاطِ|and the descendants,|165|178|1236$وَمَآ|and what|82|108|46$أُوتِىَ|was given|86|112|1237$مُوسَىٰ|(to) Musa|85|111|499$وَعِيسَىٰ|and Isa|95|121|1238$وَمَآ|and what|82|95|46$أُوتِىَ|was given|86|94|1237$ٱلنَّبِيُّونَ|(to) the Prophets|136|152|1239$مِن|from|50|66|53$رَّبِّهِمْ|their Lord.|88|104|54$لَا|Not|43|59|30$نُفَرِّقُ|we make distinction|151|167|1240$بَيْنَ|between|77|85|671$أَحَدٍ|any|55|86|961$مِّنْهُمْ|of them.|76|138|730$وَنَحْنُ|And we|76|138|319$لَهُۥ|to Him|62|124|977$مُسْلِمُونَ|(are) submissive. `|146|177|1210$","juz":1,"ruku":17,"manzil":1,"hizbQuarter":8,"sajda":false,"isSurahStart":false},{"surahNumber":2,"surahName":"سُورَةُ البَقَرَةِ","surahEnglishName":"Al-Baqara","ayahNumber":137,"text":"فَإِنْ|So if|53|70|227$ءَامَنُواْ|they believe[d]|121|155|84$بِمِثْلِ|in (the) like|96|130|1241$مَآ|(of) what|83|117|262$ءَامَنتُم|you have believed|140|174|1242$بِهِۦ|in [it],|62|79|204$فَقَدِ|then indeed,|103|115|1243$ٱهْتَدَواْ‌ۖ|they are (rightly) guided.|187|211|1244$وَّإِن|But if|58|82|213$تَوَلَّوْاْ|they turn away,|127|151|1245$فَإِنَّمَا|then only|82|106|1086$هُمْ|they|50|62|49$فِى|(are) in|69|78|89$شِقَاقٍ‌ۖ|dissension.|92|111|1246$فَسَيَكْفِيكَهُمُ ٱللَّهُ‌ۚ|So Allah will suffice you against them,|272|291|1247$وَهُوَ|and He|66|85|305$ٱلسَّمِيعُ|(is) the All-Hearing,|150|160|1170$ٱلْعَلِيمُ|the All-Knowing.|128|128|342$","juz":1,"ruku":17,"manzil":1,"hizbQuarter":8,"sajda":false,"isSurahStart":false},{"surahNumber":2,"surahName":"سُورَةُ البَقَرَةِ","surahEnglishName":"Al-Baqara","ayahNumber":138,"text":"صِبْغَةَ|(The) color (religion)|157|170|1248$ٱللَّهِ‌ۖ|(of) Allah!|86|113|606$وَمَنْ|And who|77|104|1012$أَحْسَنُ|(is) better|88|115|1249$مِنَ|than|50|77|156$ٱللَّهِ صِبْغَةً‌ۖ|Allah at coloring?|133|146|1250$وَنَحْنُ|And we|76|172|319$لَهُۥ|to Him|62|255|977$عَـٰبِدُونَ|(are) worshippers.|141|238|1251$","juz":1,"ruku":17,"manzil":1,"hizbQuarter":8,"sajda":false,"isSurahStart":false},{"surahNumber":2,"surahName":"سُورَةُ البَقَرَةِ","surahEnglishName":"Al-Baqara","ayahNumber":139,"text":"قُلْ|Say,|50|58|765$أَتُحَآجُّونَنَا|`Do you argue with us|169|186|1252$فِى|about|58|75|89$ٱللَّهِ|Allah|53|70|2$وَهُوَ|while He|75|92|305$رَبُّنَا|(is) our Lord|101|118|1253$وَرَبُّكُمْ|and your Lord?|118|126|1254$وَلَنَآ|And for us|88|103|1255$أَعْمَـٰلُنَا|(are) our deeds|123|153|1256$وَلَكُمْ|and for you|96|126|387$أَعْمَـٰلُكُمْ|(are) your deeds|131|161|1257$وَنَحْنُ|and we|76|106|319$لَهُۥ|to Him|62|77|977$مُخْلِصُونَ|(are) sincere.|115|115|1258$","juz":1,"ruku":17,"manzil":1,"hizbQuarter":8,"sajda":false,"isSurahStart":false},{"surahNumber":2,"surahName":"سُورَةُ البَقَرَةِ","surahEnglishName":"Al-Baqara","ayahNumber":140,"text":"أَمْ|Or|38|49|62$تَقُولُونَ|(do) you say|105|126|771$إِنَّ|that|48|69|58$إِبْرَٲهِــۧمَ|Ibrahim|90|111|1127$وَإِسْمَـٰعِيلَ|and Ismail|115|136|1145$وَإِسْحَـٰقَ|and Ishaq|101|122|1221$وَيَعْقُوبَ|and Yaqub|100|111|1235$وَٱلْأَسْبَاطَ|and the descendants|160|173|1259$كَانُواْ|were|69|96|94$هُودًا|Jews|66|93|1036$أَوْ|or|41|68|154$نَصَـٰرَىٰ‌ۗ|Christians?`|99|126|1037$قُلْ|Say,|50|77|765$ءَأَنتُمْ|`Are you|79|92|1260$أَعْلَمُ|better knowing|119|137|324$أَمِ ٱللَّهُ‌ۗ|or (is) Allah?`|111|147|1261$وَمَنْ|And who|77|113|1012$أَظْلَمُ|(is) more unjust|125|161|1060$مِمَّن|than (the one) who|150|168|1061$كَتَمَ|concealed|87|94|1262$شَهَـٰدَةً|a testimony|98|112|1263$عِندَهُۥ|(that) he has|109|123|1264$مِنَ|from|50|64|156$ٱللَّهِ‌ۗ|Allah?|58|72|606$وَمَا|And not|72|86|46$ٱللَّهُ|(is) Allah|78|92|123$بِغَـٰفِلٍ|unaware|76|83|723$عَمَّا|of what|71|322|724$تَعْمَلُونَ|you do.|92|343|725$","juz":1,"ruku":17,"manzil":1,"hizbQuarter":8,"sajda":false,"isSurahStart":false},{"surahNumber":2,"surahName":"سُورَةُ البَقَرَةِ","surahEnglishName":"Al-Baqara","ayahNumber":141,"text":"تِلْكَ|This|54|68|1038$أُمَّةٌ|(was) a community|147|175|1224$قَدْ خَلَتْ‌ۖ|(which) has passed away.|194|222|1225$لَهَا|For it|55|83|1226$مَا|what|53|81|262$كَسَبَتْ|it earned|81|95|1265$وَلَكُم|and for you|96|110|387$مَّا|what|53|81|262$كَسَبْتُمْ‌ۖ|you have earned.|136|164|1228$وَلَا|And not|72|100|25$تُسْــَٔلُونَ|you will be asked|133|161|1229$عَمَّا|about what|96|110|724$كَانُواْ|they used to|105|339|94$يَعْمَلُونَ|do.|92|326|912$","juz":1,"ruku":17,"manzil":1,"hizbQuarter":8,"sajda":false,"isSurahStart":false}]}