{"page":188,"ayahs":[{"surahNumber":9,"surahName":"سُورَةُ التَّوۡبَةِ","surahEnglishName":"At-Tawba","ayahNumber":7,"text":"كَیْفَ یَكُوْنُ لِلْمُشْرِكِیْنَ عَهْدٌ عِنْدَ اللّٰهِ وَعِنْدَ رَسُوْلِهٖۤ اِلَّا الَّذِیْنَ عٰهَدْتُّمْ عِنْدَ الْمَسْجِدِ الْحَرَامِ ۚ فَمَا اسْتَقَامُوْا لَكُمْ فَاسْتَقِیْمُوْا لَهُمْ ؕ اِنَّ اللّٰهَ یُحِبُّ الْمُتَّقِیْنَ ۟","juz":10,"ruku":157,"hizbQuarter":75,"sajda":false,"isSurahStart":false},{"surahNumber":9,"surahName":"سُورَةُ التَّوۡبَةِ","surahEnglishName":"At-Tawba","ayahNumber":8,"text":"كَیْفَ وَاِنْ یَّظْهَرُوْا عَلَیْكُمْ لَا یَرْقُبُوْا فِیْكُمْ اِلًّا وَّلَا ذِمَّةً ؕ یُرْضُوْنَكُمْ بِاَفْوَاهِهِمْ وَتَاْبٰی قُلُوْبُهُمْ ۚ وَاَكْثَرُهُمْ فٰسِقُوْنَ ۟ۚ","juz":10,"ruku":157,"hizbQuarter":75,"sajda":false,"isSurahStart":false},{"surahNumber":9,"surahName":"سُورَةُ التَّوۡبَةِ","surahEnglishName":"At-Tawba","ayahNumber":9,"text":"اِشْتَرَوْا بِاٰیٰتِ اللّٰهِ ثَمَنًا قَلِیْلًا فَصَدُّوْا عَنْ سَبِیْلِهٖ ؕ اِنَّهُمْ سَآءَ مَا كَانُوْا یَعْمَلُوْنَ ۟","juz":10,"ruku":157,"hizbQuarter":75,"sajda":false,"isSurahStart":false},{"surahNumber":9,"surahName":"سُورَةُ التَّوۡبَةِ","surahEnglishName":"At-Tawba","ayahNumber":10,"text":"لَا یَرْقُبُوْنَ فِیْ مُؤْمِنٍ اِلًّا وَّلَا ذِمَّةً ؕ وَاُولٰٓىِٕكَ هُمُ الْمُعْتَدُوْنَ ۟","juz":10,"ruku":157,"hizbQuarter":75,"sajda":false,"isSurahStart":false},{"surahNumber":9,"surahName":"سُورَةُ التَّوۡبَةِ","surahEnglishName":"At-Tawba","ayahNumber":11,"text":"فَاِنْ تَابُوْا وَاَقَامُوا الصَّلٰوةَ وَاٰتَوُا الزَّكٰوةَ فَاِخْوَانُكُمْ فِی الدِّیْنِ ؕ وَنُفَصِّلُ الْاٰیٰتِ لِقَوْمٍ یَّعْلَمُوْنَ ۟","juz":10,"ruku":157,"hizbQuarter":75,"sajda":false,"isSurahStart":false},{"surahNumber":9,"surahName":"سُورَةُ التَّوۡبَةِ","surahEnglishName":"At-Tawba","ayahNumber":12,"text":"وَاِنْ نَّكَثُوْۤا اَیْمَانَهُمْ مِّنْ بَعْدِ عَهْدِهِمْ وَطَعَنُوْا فِیْ دِیْنِكُمْ فَقَاتِلُوْۤا اَىِٕمَّةَ الْكُفْرِ ۙ اِنَّهُمْ لَاۤ اَیْمَانَ لَهُمْ لَعَلَّهُمْ یَنْتَهُوْنَ ۟","juz":10,"ruku":157,"hizbQuarter":75,"sajda":false,"isSurahStart":false},{"surahNumber":9,"surahName":"سُورَةُ التَّوۡبَةِ","surahEnglishName":"At-Tawba","ayahNumber":13,"text":"اَلَا تُقَاتِلُوْنَ قَوْمًا نَّكَثُوْۤا اَیْمَانَهُمْ وَهَمُّوْا بِاِخْرَاجِ الرَّسُوْلِ وَهُمْ بَدَءُوْكُمْ اَوَّلَ مَرَّةٍ ؕ اَتَخْشَوْنَهُمْ ۚ فَاللّٰهُ اَحَقُّ اَنْ تَخْشَوْهُ اِنْ كُنْتُمْ مُّؤْمِنِیْنَ ۟","juz":10,"ruku":157,"hizbQuarter":75,"sajda":false,"isSurahStart":false}]}